README.rst
setup.py
pyspectrum2.egg-info/PKG-INFO
pyspectrum2.egg-info/SOURCES.txt
pyspectrum2.egg-info/dependency_links.txt
pyspectrum2.egg-info/requires.txt
pyspectrum2.egg-info/top_level.txt
spectrum2/__init__.py
spectrum2/backend.py
spectrum2/config.py
spectrum2/protocol_pb2.py