Metadata-Version: 1.2
Name: pyspectrum2
Version: 0.2.0
Summary: pyspectrum2 implements the Protobuf-based interface to Spectrum2 required for building Python-based backends
Home-page: https://github.com/SpectrumIM/spectrum2
Author: Steffen Vogel
Author-email: post@steffenvogel.de
License: GPL-3+
Keywords: spectrum2 xmpp im gateway transport
Platform: UNKNOWN
Classifier: License :: OSI Approved :: GNU General Public License v3 or later (GPLv3+)
Classifier: Development Status :: 4 - Beta
Classifier: Environment :: Plugins
Classifier: Operating System :: POSIX
Classifier: Topic :: Communications :: Chat
Requires-Python: >=3.0
